MANIFEST.in
README.rst
README.txt
setup.py
collective/__init__.py
collective.js.charcount.egg-info/PKG-INFO
collective.js.charcount.egg-info/SOURCES.txt
collective.js.charcount.egg-info/dependency_links.txt
collective.js.charcount.egg-info/entry_points.txt
collective.js.charcount.egg-info/namespace_packages.txt
collective.js.charcount.egg-info/not-zip-safe
collective.js.charcount.egg-info/requires.txt
collective.js.charcount.egg-info/top_level.txt
collective/js/__init__.py
collective/js/charcount/__init__.py
collective/js/charcount/configure.zcml
collective/js/charcount/testing.py
collective/js/charcount/profiles/default/browserlayer.xml
collective/js/charcount/profiles/default/jsregistry.xml
collective/js/charcount/profiles/default/metadata.xml
collective/js/charcount/resources/charcount.js
collective/js/charcount/resources/demo.html
collective/js/charcount/tests/__init__.py
collective/js/charcount/tests/test_setup.py
docs/CREDITS.rst
docs/HISTORY.rst
docs/INSTALL.rst
docs/LICENSE.GPL
docs/LICENSE.txt