Metadata-Version: 1.0
Name: collective.js.charcount
Version: 1.1
Summary: jQuery plugin dynamic character count
Home-page: https://github.com/collective/collective.js.charcount
Author: Cleber J Santos
Author-email: cleber@cleberjsantos.com.br
License: GPLv2
Keywords: count plone
Platform: UNKNOWN
Classifier: Framework :: Plone
Classifier: Framework :: Plone :: 4.2
Classifier: Framework :: Plone :: 4.3
Classifier: License :: OSI Approved :: GNU General Public License v2 (GPLv2)
Classifier: Operating System :: OS Independent
Classifier: Programming Language :: JavaScript
Classifier: Programming Language :: Python
